{
  "components": [
    {
      "data": {
        "contents_checksum": "8f1c24d273122da4020ac2106e439187e5d1d2769c75ccff72359fd4e892746f",
        "source": "",
        "type": "tar"
      },
      "dependencies": [
        "core",
        "gcloud-deps",
        "ssh-tools"
      ],
      "details": {
        "description": "Handles all core functionality for the Google Cloud CLI.",
        "display_name": "Google Cloud CLI Core Libraries (Platform Specific)"
      },
      "id": "core-nix",
      "is_configuration": false,
      "is_hidden": true,
      "is_required": true,
      "platform": {
        "operating_systems": [
          "CYGWIN",
          "LINUX",
          "MACOSX",
          "MSYS"
        ]
      },
      "platform_required": false,
      "version": {
        "build_number": 20220912133630,
        "version_string": "2022.09.12"
      }
    }
  ],
  "revision": 20220912133630,
  "schema_version": {
    "no_update": false,
    "url": "https://dl.google.com/dl/cloudsdk/channels/rapid/google-cloud-sdk.tar.gz",
    "version": 3
  },
  "version": "402.0.0"
}