{
  "components": [
    {
      "data": {
        "contents_checksum": "e77620d16f68c9c2f78b31702bfdd20085bda3c9ee8cb93263df6f92e1be0484",
        "source": "",
        "type": "tar"
      },
      "dependencies": [
        "core-nix",
        "core-win",
        "gcloud-deps",
        "ssh-tools"
      ],
      "details": {
        "description": "Handles all core functionality for the Google Cloud CLI.",
        "display_name": "Google Cloud CLI Core Libraries"
      },
      "id": "core",
      "is_configuration": false,
      "is_hidden": false,
      "is_required": true,
      "platform": {},
      "platform_required": false,
      "version": {
        "build_number": 20220506143240,
        "version_string": "2022.05.06"
      }
    }
  ],
  "revision": 20220506143240,
  "schema_version": {
    "no_update": false,
    "url": "https://dl.google.com/dl/cloudsdk/channels/rapid/google-cloud-sdk.tar.gz",
    "version": 3
  },
  "version": "385.0.0"
}