{
  "components": [
    {
      "data": {
        "contents_checksum": "4d5a46a5e0105a8750e8398522fe0901a1c4422cc649bbd10d40731d767ffcee",
        "source": "",
        "type": "tar"
      },
      "dependencies": [
        "core-nix",
        "core-win",
        "gcloud-deps",
        "ssh-tools"
      ],
      "details": {
        "description": "Handles all core functionality for the Cloud SDK.",
        "display_name": "Cloud SDK Core Libraries"
      },
      "id": "core",
      "is_configuration": false,
      "is_hidden": false,
      "is_required": true,
      "platform": {},
      "platform_required": false,
      "version": {
        "build_number": 20210409140628,
        "version_string": "2021.04.09"
      }
    }
  ],
  "revision": 20210409140628,
  "schema_version": {
    "no_update": false,
    "url": "https://dl.google.com/dl/cloudsdk/channels/rapid/google-cloud-sdk.tar.gz",
    "version": 3
  },
  "version": "336.0.0"
}