{
  "components": [
    {
      "data": {
        "contents_checksum": "97c753691211dae44da8bc17548ed581ee8c9b0f26ac552f0130262abef5d2d6",
        "source": "",
        "type": "tar"
      },
      "dependencies": [
        "core",
        "gsutil-nix",
        "gsutil-win"
      ],
      "details": {
        "description": "Provides the gsutil tool for interacting with Google Cloud Storage.",
        "display_name": "Cloud Storage Command Line Tool"
      },
      "id": "gsutil",
      "is_configuration": false,
      "is_hidden": false,
      "is_required": false,
      "platform": {},
      "platform_required": false,
      "version": {
        "build_number": 20211004160453,
        "version_string": "5.3"
      }
    }
  ],
  "revision": 20211004160453,
  "schema_version": {
    "no_update": false,
    "url": "https://dl.google.com/dl/cloudsdk/channels/rapid/google-cloud-sdk.tar.gz",
    "version": 3
  },
  "version": "360.0.0"
}